highway_dsl/__init__.py
highway_dsl/diagrams.py
highway_dsl/graphviz_export.py
highway_dsl/mcp_client_server.py
highway_dsl/mcp_server.py
highway_dsl/workflow_dsl.py
highway_dsl-2.1.3.dist-info/licenses/LICENSE
highway_dsl-2.1.3.dist-info/METADATA
highway_dsl-2.1.3.dist-info/WHEEL
highway_dsl-2.1.3.dist-info/entry_points.txt
highway_dsl-2.1.3.dist-info/top_level.txt
highway_dsl-2.1.3.dist-info/RECORD
