Metadata-Version: 2.4
Name: highway_dsl
Version: 2.1.3
Summary: LTS Stable: Domain-specific language (DSL) for defining production-grade workflows with explicit coordination, event-driven patterns, and Temporal-style join operators.
Author-email: Farseed Ashouri <farseed.ashouri@gmail.com>
License: MIT
Project-URL: Homepage, https://github.com/rodmena-limited/highway_dsl
Project-URL: Issues, https://github.com/rodmena-limited/highway_dsl/issues
Classifier: Programming Language :: Python :: 3
Classifier: License :: OSI Approved :: MIT License
Classifier: Operating System :: OS Independent
Requires-Python: >=3.10
License-File: LICENSE
Requires-Dist: pydantic>=2.12.3
Requires-Dist: pyyaml>=6.0
Provides-Extra: dev
Requires-Dist: pytest>=7.0.0; extra == "dev"
Requires-Dist: mypy>=1.0.0; extra == "dev"
Requires-Dist: types-PyYAML>=6.0.0; extra == "dev"
Requires-Dist: pytest-cov>=2.12.1; extra == "dev"
Provides-Extra: mcp
Requires-Dist: mcp[cli]>=1.0.0; extra == "mcp"
Dynamic: license-file
